gatoniel_utils/__init__.py
gatoniel_utils/example.py
gatoniel_utils/py.typed
gatoniel_utils/segmentation/__init__.py
gatoniel_utils/segmentation/colony.py
gatoniel_utils-0.1.0.dist-info/LICENSE
gatoniel_utils-0.1.0.dist-info/WHEEL
gatoniel_utils-0.1.0.dist-info/METADATA
gatoniel_utils-0.1.0.dist-info/RECORD
