Metadata-Version: 2.1
Name: gatoniel-utils
Version: 0.1.0
Summary: Library with utils and helpers for myself.
Home-page: https://github.com/gatoniel/gatoniel-utils
License: MIT
Requires-Python: >=3.7,<4.0
Classifier: Development Status :: 3 - Alpha
Classifier: Intended Audience :: Developers
Classifier: License :: OSI Approved :: MIT License
Classifier: Operating System :: OS Independent
Classifier: Programming Language :: Python :: 3
Classifier: Programming Language :: Python :: 3.7
Classifier: Programming Language :: Python :: 3.8
Classifier: Programming Language :: Python :: 3.9
Classifier: Topic :: Software Development :: Libraries :: Python Modules
Requires-Dist: numpy (>=1.20.1,<2.0.0)
Requires-Dist: scikit-image (>=0.18.1,<0.19.0)
Requires-Dist: scipy (>=1.6.1,<2.0.0)
Project-URL: Repository, https://github.com/gatoniel/gatoniel-utils
